publicator/__init__.py
publicator/cli.py
publicator/config.py
publicator/git.py
publicator/github.py
publicator/poetry.py
publicator/shell.py
publicator-1.3.0.dist-info/entry_points.txt
publicator-1.3.0.dist-info/LICENSE.md
publicator-1.3.0.dist-info/WHEEL
publicator-1.3.0.dist-info/METADATA
publicator-1.3.0.dist-info/RECORD
