Metadata-Version: 2.1
Name: publicator
Version: 1.3.0
Summary: A better poetry publish experience.
Home-page: https://pypi.org/project/publicator/
License: MIT
Keywords: poetry,tools,packaging
Author: Niko Heikkilä
Author-email: niko.heikkila@futurice.com
Requires-Python: >=3.8,<4.0.0
Classifier: License :: OSI Approved :: MIT License
Classifier: Programming Language :: Python :: 3
Classifier: Programming Language :: Python :: 3.8
Classifier: Programming Language :: Python :: 3.9
Classifier: Programming Language :: Python :: 3.10
Requires-Dist: colorama (>=0.4.4,<0.5.0)
Requires-Dist: parse (>=1.19.0,<2.0.0)
Requires-Dist: safe-assert (>=0.2.0,<0.3.0)
Requires-Dist: semmy (>=1.0.0,<2.0.0)
Requires-Dist: tomli (==2.0.1)
Requires-Dist: typer[all] (>=0.6.1,<0.7.0)
Project-URL: Bug Tracker, https://github.com/nikoheikkila/publicator/issues
Project-URL: Documentation, https://github.com/nikoheikkila/publicator/blob/main/README.md
Project-URL: Discussions, https://github.com/nikoheikkila/publicator/discussions
Project-URL: Repository, https://github.com/nikoheikkila/publicator
